pid/__init__.py
pid/pid.py
mix_pid-0.0.2.dist-info/LICENSE.txt
mix_pid-0.0.2.dist-info/METADATA
mix_pid-0.0.2.dist-info/WHEEL
mix_pid-0.0.2.dist-info/top_level.txt
mix_pid-0.0.2.dist-info/RECORD
