Metadata-Version: 2.1
Name: mix-pid
Version: 0.0.2
Summary: 锅炉压力的PID控制算法
Home-page: https://github.com/xiangyangkan/pid
Author: xiangyangkan
Author-email: xiangyangkan@outlook.com
License: UNKNOWN
Project-URL: Documentation, https://mix-pid.readthedocs.io/
Keywords: pid controller control
Platform: UNKNOWN
Classifier: Development Status :: 3 - Alpha
Classifier: Intended Audience :: Developers
Classifier: Topic :: Software Development :: Build Tools
Classifier: License :: OSI Approved :: MIT License
Classifier: Programming Language :: Python :: 2
Classifier: Programming Language :: Python :: 3
